cmpd/__init__.py
cmpd/main.py
cmpd-0.1.5.dist-info/LICENSE
cmpd-0.1.5.dist-info/METADATA
cmpd-0.1.5.dist-info/WHEEL
cmpd-0.1.5.dist-info/entry_points.txt
cmpd-0.1.5.dist-info/top_level.txt
cmpd-0.1.5.dist-info/RECORD
