Metadata-Version: 2.1
Name: cmpd
Version: 0.1.5
Summary: A command line tool that compares data.
Author-email: Zaid Waqi <zaidwaqi@gmail.com>
License: MIT
Project-URL: Homepage, https://github.com/zaidwaqi/compare-data
Project-URL: Issues, https://github.com/pypa/zaidwaqi/compare-data/issues
Classifier: Programming Language :: Python :: 3
Classifier: License :: OSI Approved :: MIT License
Classifier: Operating System :: OS Independent
Requires-Python: >=3.11
License-File: LICENSE
Requires-Dist: pyarrow
Requires-Dist: pandas
Requires-Dist: numpy
